eve/__init__.py
eve/auth.py
eve/default_settings.py
eve/endpoints.py
eve/exceptions.py
eve/flaskapp.py
eve/logging.py
eve/render.py
eve/utils.py
eve/validation.py
eve/versioning.py
eve/io/__init__.py
eve/io/base.py
eve/io/media.py
eve/io/mongo/__init__.py
eve/io/mongo/flask_pymongo.py
eve/io/mongo/geo.py
eve/io/mongo/media.py
eve/io/mongo/mongo.py
eve/io/mongo/parser.py
eve/io/mongo/validation.py
eve/methods/__init__.py
eve/methods/common.py
eve/methods/delete.py
eve/methods/get.py
eve/methods/patch.py
eve/methods/post.py
eve/methods/put.py
eve-2.2.3.dist-info/licenses/AUTHORS
eve-2.2.3.dist-info/licenses/LICENSE
eve-2.2.3.dist-info/METADATA
eve-2.2.3.dist-info/WHEEL
eve-2.2.3.dist-info/top_level.txt
eve-2.2.3.dist-info/RECORD
