Metadata-Version: 2.4
Name: Eve
Version: 2.2.3
Summary: Python REST API for Humans.
Home-page: http://python-eve.org
Author: Nicola Iarocci
Author-email: eve@nicolaiarocci.com
License: BSD
Project-URL: Documentation, http://python-eve.org
Project-URL: Code, https://github.com/pyeve/eve
Project-URL: Issue tracker, https://github.com/pyeve/eve/issues
Platform: any
Classifier: Development Status :: 5 - Production/Stable
Classifier: Environment :: Web Environment
Classifier: Intended Audience :: Developers
Classifier: License :: OSI Approved :: BSD License
Classifier: Operating System :: OS Independent
Classifier: Programming Language :: Python
Classifier: Programming Language :: Python :: 3.9
Classifier: Programming Language :: Python :: 3.10
Classifier: Programming Language :: Python :: 3.11
Classifier: Programming Language :: Python :: 3.12
Classifier: Topic :: Internet :: WWW/HTTP :: Dynamic Content
Classifier: Topic :: Internet :: WWW/HTTP :: WSGI :: Application
Classifier: Topic :: Software Development :: Libraries :: Application Frameworks
Classifier: Topic :: Software Development :: Libraries :: Python Modules
Requires-Python: >=3.7
License-File: LICENSE
License-File: AUTHORS
Requires-Dist: cerberus<2.0,>=1.1
Requires-Dist: events<0.4,>=0.3
Requires-Dist: flask
Requires-Dist: pymongo
Requires-Dist: simplejson<4.0,>=3.3.0
Provides-Extra: docs
Requires-Dist: sphinx; extra == "docs"
Requires-Dist: alabaster; extra == "docs"
Requires-Dist: doc8; extra == "docs"
Provides-Extra: tests
Requires-Dist: redis; extra == "tests"
Requires-Dist: testfixtures; extra == "tests"
Requires-Dist: pytest; extra == "tests"
Requires-Dist: tox; extra == "tests"
Provides-Extra: dev
Requires-Dist: redis; extra == "dev"
Requires-Dist: testfixtures; extra == "dev"
Requires-Dist: pytest; extra == "dev"
Requires-Dist: tox; extra == "dev"
Requires-Dist: sphinx; extra == "dev"
Requires-Dist: alabaster; extra == "dev"
Requires-Dist: doc8; extra == "dev"
Dynamic: author
Dynamic: author-email
Dynamic: classifier
Dynamic: description
Dynamic: description-content-type
Dynamic: home-page
Dynamic: license
Dynamic: license-file
Dynamic: platform
Dynamic: project-url
Dynamic: provides-extra
Dynamic: requires-dist
Dynamic: requires-python
Dynamic: summary
